{"type":"sprite","x":0,"y":0,"name":"","0":{"x":136,"y":-123,"name":"needleDragR","type":"sprite","r":0,"sx":6.49969482421875,"sy":0.5,"a":1,"skewX":0,"skewY":3.141592653589793,"0":{"type":"shape","path":[255,20,0,2,0,0,2,0,20,2,20,20,2,20,0,2,20,0,1,1,16777215,33]}},"1":{"x":-139,"y":-123,"name":"needleDragL","type":"sprite","r":0,"sx":6.5,"sy":0.5,"a":1,"skewX":0,"skewY":0,"0":{"type":"shape","path":[255,20,0,2,0,0,2,0,20,2,20,20,2,20,0,2,20,0,1,1,16777215,33]}},"2":{"x":-129,"y":-132,"name":"bp0","type":"sprite","r":0,"sx":1,"sy":1,"a":1,"skewX":0,"skewY":0,"0":{"type":"shape","path":[255,20,0,2,0,0,2,0,20,2,20,20,2,20,0,2,20,0,1,1,16777215,33]}},"3":{"x":105,"y":-132,"name":"bp1","type":"sprite","r":0,"sx":1,"sy":1,"a":1,"skewX":0,"skewY":0,"0":{"type":"shape","path":[255,20,0,2,0,0,2,0,20,2,20,20,2,20,0,2,20,0,1,1,16777215,33]}},"4":{"x":-2,"y":55,"name":"light","type":"nbMovie","r":0,"sx":1,"sy":1,"a":1,"skewX":0,"skewY":0,"0":{"index":1,"0":{"type":"bitmap","libName":"关.png","x":-21,"y":-21,"r":0,"sx":1,"sy":1,"skewX":0,"skewY":0}},"1":{"index":1,"0":{"type":"bitmap","libName":"开.png","x":-21,"y":-21,"r":0,"sx":1,"sy":1,"skewX":0,"skewY":0}}},"5":{"x":-107,"y":73.95,"name":"rot0","type":"sprite","r":0,"sx":0.9999847412109375,"sy":0.9999847412109375,"a":1,"skewX":0,"skewY":0,"0":{"type":"bitmap","libName":"旋钮指针.png","x":-17,"y":-17,"r":0,"sx":1,"sy":1,"skewX":0,"skewY":0},"1":{"type":"bitmap","libName":"Bitmap 1","x":-32.5,"y":-32.5,"r":0,"sx":1,"sy":1,"skewX":0,"skewY":0}},"6":{"x":105,"y":75.1,"name":"rot1","type":"sprite","r":0,"sx":0.999969482421875,"sy":0.999969482421875,"a":1,"skewX":0,"skewY":0,"0":{"type":"bitmap","libName":"旋钮指针.png","x":-17,"y":-17,"r":0,"sx":1,"sy":1,"skewX":0,"skewY":0},"1":{"type":"bitmap","libName":"Bitmap 1","x":-32.5,"y":-32.5,"r":0,"sx":1,"sy":1,"skewX":0,"skewY":0}},"7":{"x":0,"y":0,"name":"bg","type":"sprite","r":0,"sx":1,"sy":1,"a":1,"skewX":0,"skewY":0,"0":{"type":"bitmap","libName":"高压感应圈.png","x":-216,"y":-137,"r":0,"sx":1,"sy":1,"skewX":0,"skewY":0}},"8":{"x":137,"y":-118,"name":"needleR","type":"sprite","r":0,"sx":1,"sy":1,"a":1,"skewX":0,"skewY":3.141592653589793,"0":{"type":"bitmap","libName":"针左.png","x":0,"y":-2,"r":0,"sx":1,"sy":1,"skewX":0,"skewY":0}},"9":{"x":-147,"y":-118,"name":"needleL","type":"sprite","r":0,"sx":1,"sy":1,"a":1,"skewX":0,"skewY":0,"0":{"type":"bitmap","libName":"针左.png","x":0,"y":-2,"r":0,"sx":1,"sy":1,"skewX":0,"skewY":0}}}