{"frames":{"Oilslick/Bitmap 2":{"frame":{"x":2,"y":2,"w":741,"h":374},"rotated":false,"trimmed":false,"spriteSourceSize":{"x":0,"y":0,"w":741,"h":374},"sourceSize":{"w":741,"h":374}},"Oilslick/坐标值.png":{"frame":{"x":2,"y":378,"w":755,"h":280},"rotated":false,"trimmed":false,"spriteSourceSize":{"x":0,"y":0,"w":755,"h":280},"sourceSize":{"w":755,"h":280}},"Oilslick/油酸酒精溶液.png":{"frame":{"x":759,"y":378,"w":164,"h":137},"rotated":false,"trimmed":false,"spriteSourceSize":{"x":0,"y":0,"w":164,"h":137},"sourceSize":{"w":164,"h":137}},"Oilslick/注射剂1.png":{"frame":{"x":925,"y":378,"w":45,"h":165},"rotated":false,"trimmed":false,"spriteSourceSize":{"x":0,"y":0,"w":45,"h":165},"sourceSize":{"w":45,"h":165}},"Oilslick/注射剂2.png":{"frame":{"x":972,"y":378,"w":27,"h":115},"rotated":false,"trimmed":false,"spriteSourceSize":{"x":0,"y":0,"w":27,"h":115},"sourceSize":{"w":27,"h":115}},"Oilslick/痱子粉.png":{"frame":{"x":2,"y":660,"w":63,"h":95},"rotated":false,"trimmed":false,"spriteSourceSize":{"x":0,"y":0,"w":63,"h":95},"sourceSize":{"w":63,"h":95}},"Oilslick/盛水浅盘1.png":{"frame":{"x":67,"y":660,"w":720,"h":356},"rotated":false,"trimmed":false,"spriteSourceSize":{"x":0,"y":0,"w":720,"h":356},"sourceSize":{"w":720,"h":356}},"Oilslick/盛水浅盘2.png":{"frame":{"x":2,"y":1018,"w":720,"h":356},"rotated":false,"trimmed":false,"spriteSourceSize":{"x":0,"y":0,"w":720,"h":356},"sourceSize":{"w":720,"h":356}},"Oilslick/笔.png":{"frame":{"x":724,"y":1018,"w":28,"h":220},"rotated":false,"trimmed":false,"spriteSourceSize":{"x":0,"y":0,"w":28,"h":220},"sourceSize":{"w":28,"h":220}}},"meta":{"app":"Adobe Flash Professional","version":"13.0.0.759","image":"Oilslick.png","format":"RGBA8888","size":{"w":1024,"h":2048},"scale":"1"}}