{"formData":[],"seCompData":{"data":[]},"phyData":{"dataVersion":3,"id":"14759830742857","properties":{"data":{"containsVipequ":false,"version":1,"showElecLine":true,"SHOWEQUVALUE":true,"SHOWTIPPAO":true,"SHOW_FLAG_LABEL":true,"VOLUME":1,"OPEN_ANGLE":false,"SHOW_REFLECT":false,"SHOW_DIRECTION":false,"SHOW_ZULI":false,"COMP_MESS":true,"BTN_NAME":true,"ZULI_NUM":9.8,"confVer":"1.0.0","moduleData":{},"view":{"x":1507.4734749334561,"y":-3803.421297989018,"scaleX":1.0468565798149,"scaleY":1.0468565798149},"backgroundColorImg":{"colors":{"direction":0,"arr":["#343941"],"style":{"background":"#343941"}},"textureSelected":0},"dataArr":[{"uid":1475981756780,"classname":"ElecLampAndHolder","cateid":"1","positionX":219.30107272401847,"positionY":4698.301438135532,"rotation":0,"loadLevel":5,"notexture":"0","isBreak":false,"flagLabel":"L2","Resistance":2.5,"Power":0,"hasReversal":false,"hasMagReversal":false,"flabel1txt":"L","flabel2txt":"2","ratedV":3,"ratedP":3.6,"breakV":3.13,"isShortCircuit":false,"posts":[{"UID":"4689130185707"},{"UID":"4293282618939"}]},{"uid":1475983011336,"classname":"ElecSinglePloeSingleThrowSwitch","cateid":"1","positionX":-515.2326017871542,"positionY":4680.584485238833,"rotation":0,"loadLevel":5,"notexture":"0","isBreak":true,"flagLabel":"S3","Resistance":0.00001,"Power":0,"hasReversal":false,"hasMagReversal":false,"flabel1txt":"S","flabel2txt":"2","daoRotation":-0.48,"posts":[{"UID":"4344413186985"},{"UID":"4549864019561"}]},{"uid":1475983011174,"classname":"ElecSinglePloeSingleThrowSwitch","cateid":"1","positionX":-502.2271324041916,"positionY":4418.093357183552,"rotation":0,"loadLevel":5,"notexture":"0","isBreak":true,"flagLabel":"S2","Resistance":0.00001,"Power":0,"hasReversal":false,"hasMagReversal":false,"flabel1txt":"S","flabel2txt":"1","daoRotation":-0.48,"posts":[{"UID":"3548538986035"},{"UID":"3455244302400"}]},{"uid":1475983011039,"classname":"ElecSinglePloeSingleThrowSwitch","cateid":"1","positionX":-493.54679052383153,"positionY":4134.586623056893,"rotation":0,"loadLevel":5,"notexture":"0","isBreak":true,"flagLabel":"S1","Resistance":0.00001,"Power":0,"hasReversal":false,"hasMagReversal":false,"flabel1txt":"S","flabel2txt":" ","daoRotation":-0.65522274305337,"posts":[{"UID":"4465687487214"},{"UID":"4315664577905"}]},{"uid":1475981756609,"classname":"ElecLampAndHolder","cateid":"1","positionX":206.96602998891854,"positionY":4438.145377421552,"rotation":0,"loadLevel":5,"notexture":"0","isBreak":false,"flagLabel":"L1","Resistance":2.5,"Power":0,"hasReversal":false,"hasMagReversal":false,"flabel1txt":"L","flabel2txt":"1","ratedV":3,"ratedP":3.6,"breakV":3.13,"isShortCircuit":false,"posts":[{"UID":"3326635357285"},{"UID":"4404253394992"}]},{"uid":1475981753679,"classname":"BatteryHolder","cateid":"1","positionX":143.91987614281857,"positionY":4141.591825080693,"rotation":0,"loadLevel":5,"notexture":"0","isBreak":false,"flagLabel":"E1","Resistance":0.00001,"Power":3,"hasReversal":false,"hasMagReversal":false,"flabel1txt":" ","flabel2txt":" ","posts":[{"UID":"1568882692090"},{"UID":"3506113021412"}]},{"uid":1475983034397,"classname":"ElecWire","cateid":"1","positionX":1276,"positionY":983,"rotation":0,"loadLevel":4,"notexture":"0","isBreak":false,"Resistance":0.00001,"Power":0,"hasReversal":false,"hasMagReversal":false,"isDrawType":false,"colorIndex":0,"h1_x":-1687.9326017871542,"h1_y":3722.2344852388323,"h2_x":-1143.1989272759815,"h2_y":3717.4014381355328,"h1IsNearToBinding":true,"h2IsNearToBinding":true,"post0":{"UID":"4131299872867","driver":"4549864019561"},"post1":{"UID":"4407806753381","driver":"4689130185707"},"posts":[{"UID":"4131299872867"},{"UID":"4407806753381"}],"pArr":[{"x":-1687.9326017871542,"y":3722.2344852388323},{"x":-1143.1989272759815,"y":3717.4014381355328}]},{"uid":1475983034245,"classname":"ElecWire","cateid":"1","positionX":1266,"positionY":933,"rotation":0,"loadLevel":4,"notexture":"0","isBreak":false,"Resistance":0.00001,"Power":0,"hasReversal":false,"hasMagReversal":false,"isDrawType":false,"colorIndex":0,"h1_x":-1889.2826017871541,"h1_y":3772.2344852388323,"h2_x":-1876.2771324041914,"h2_y":3509.743357183552,"h1IsNearToBinding":true,"h2IsNearToBinding":true,"post0":{"UID":"4289963855051","driver":"4344413186985"},"post1":{"UID":"4509797219421","driver":"3548538986035"},"posts":[{"UID":"4289963855051"},{"UID":"4509797219421"}],"pArr":[{"x":-1889.2826017871541,"y":3772.2344852388323},{"x":-1876.2771324041914,"y":3509.743357183552}]},{"uid":1475983033965,"classname":"ElecWire","cateid":"1","positionX":1246,"positionY":833,"rotation":0,"loadLevel":4,"notexture":"0","isBreak":false,"Resistance":0.00001,"Power":0,"hasReversal":false,"hasMagReversal":false,"isDrawType":false,"colorIndex":0,"h1_x":-941.1489272759816,"h1_y":3867.4014381355328,"h2_x":-953.4839700110815,"h2_y":3607.245377421553,"h1IsNearToBinding":true,"h2IsNearToBinding":true,"post0":{"UID":"4439974730489","driver":"4293282618939"},"post1":{"UID":"3925753328727","driver":"4404253394992"},"posts":[{"UID":"4439974730489"},{"UID":"3925753328727"}],"pArr":[{"x":-941.1489272759816,"y":3867.4014381355328},{"x":-953.4839700110815,"y":3607.245377421553}]},{"uid":1475983033615,"classname":"ElecWire","cateid":"1","positionX":1226,"positionY":733,"rotation":0,"loadLevel":4,"notexture":"0","isBreak":false,"Resistance":0.00001,"Power":0,"hasReversal":false,"hasMagReversal":false,"isDrawType":false,"colorIndex":0,"h1_x":-1616.2467905238316,"h1_y":3426.2366230568923,"h2_x":-1242.0801238571814,"h2_y":3428.591825080692,"h1IsNearToBinding":true,"h2IsNearToBinding":true,"post0":{"UID":"3792822016826","driver":"4315664577905"},"post1":{"UID":"3517783626243","driver":"1568882692090"},"posts":[{"UID":"3792822016826"},{"UID":"3517783626243"}],"pArr":[{"x":-1616.2467905238316,"y":3426.2366230568923},{"x":-1242.0801238571814,"y":3428.591825080692}]},{"uid":1475983034085,"classname":"ElecWire","cateid":"1","positionX":1256,"positionY":883,"rotation":0,"loadLevel":4,"notexture":"0","isBreak":false,"Resistance":0.00001,"Power":0,"hasReversal":false,"hasMagReversal":false,"isDrawType":false,"colorIndex":0,"h1_x":-1857.5967905238315,"h1_y":3276.2366230568923,"h2_x":-1866.2771324041914,"h2_y":3559.743357183552,"h1IsNearToBinding":true,"h2IsNearToBinding":true,"post0":{"UID":"3262792911927","driver":"4465687487214"},"post1":{"UID":"1568882691788","driver":"3548538986035"},"posts":[{"UID":"3262792911927"},{"UID":"1568882691788"}],"pArr":[{"x":-1857.5967905238315,"y":3276.2366230568923},{"x":-1866.2771324041914,"y":3559.743357183552}]},{"uid":1475983033774,"classname":"ElecWire","cateid":"1","positionX":1236,"positionY":783,"rotation":0,"loadLevel":4,"notexture":"0","isBreak":false,"Resistance":0.00001,"Power":0,"hasReversal":false,"hasMagReversal":false,"isDrawType":false,"colorIndex":0,"h1_x":-1634.9271324041915,"h1_y":3659.743357183552,"h2_x":-1115.5339700110815,"h2_y":3657.245377421553,"h1IsNearToBinding":true,"h2IsNearToBinding":true,"post0":{"UID":"4094088643510","driver":"3455244302400"},"post1":{"UID":"4311240352188","driver":"3326635357285"},"posts":[{"UID":"4094088643510"},{"UID":"4311240352188"}],"pArr":[{"x":-1634.9271324041915,"y":3659.743357183552},{"x":-1115.5339700110815,"y":3657.245377421553}]},{"uid":1475983048710,"classname":"ElecWire","cateid":"1","positionX":1286,"positionY":1033,"rotation":0,"loadLevel":4,"notexture":"0","isBreak":false,"Resistance":0.00001,"Power":0,"hasReversal":false,"hasMagReversal":false,"isDrawType":false,"colorIndex":0,"h1_x":-993.4839700110815,"h1_y":3407.245377421553,"h2_x":-977.080123857181,"h2_y":3128.5918250806917,"h1IsNearToBinding":true,"h2IsNearToBinding":true,"post0":{"UID":"3471107626977","driver":"4404253394992"},"post1":{"UID":"3848294602283","driver":"3506113021412"},"posts":[{"UID":"3471107626977"},{"UID":"3848294602283"}],"pArr":[{"x":-993.4839700110815,"y":3407.245377421553},{"x":-977.080123857181,"y":3128.5918250806917}]}]},"title":"探究并联电路的特点"}}}