{"formData":[],"seCompData":{"seCompArr":[]},"phyData":{"dataVersion":3,"id":1499654071885,"properties":{"data":{"containsVipequ":true,"version":1,"showElecLine":true,"SHOWEQUVALUE":true,"SHOWTIPPAO":true,"SHOW_FLAG_LABEL":true,"VOLUME":1,"OPEN_ANGLE":false,"SHOW_REFLECT":false,"SHOW_DIRECTION":false,"SHOW_ZULI":false,"SHOW_DIAN_CHANG":false,"SHOW_CIGAN":false,"SHOW_DENG_SHI":false,"COMP_MESS":true,"ZULI_NUM":9.8,"confVer":"1.0.0","moduleData":{},"view":{"x":1420.232502751521,"y":-3269.5669964592726,"scaleX":0.9493745839581037,"scaleY":0.9493745839581037},"backgroundColorImg":{"colors":{"direction":0,"arr":["#343941"],"style":{"background":"#343941"}},"textureSelected":0},"dataArr":[{"uid":1499653899984,"classname":"BatteryHolder","cateid":"1","positionX":-610.9923056185506,"positionY":4561.7238763979085,"rotation":0,"loadLevel":5,"notexture":"0","isBreak":false,"flagLabel":"E1","Resistance":"2","Power":1.5,"hasReversal":false,"hasMagReversal":false,"flabel1txt":"E","flabel2txt":"1","bgCurrentFrame":0},{"uid":1499653895348,"classname":"ElecLampAndHolder","cateid":"1","positionX":-278.6251654748359,"positionY":3853.0537689417533,"rotation":0,"loadLevel":5,"notexture":"0","isBreak":false,"flagLabel":"L1","Resistance":10,"Power":0,"hasReversal":false,"hasMagReversal":false,"flabel1txt":"L","flabel2txt":"1","ratedV":6,"ratedP":"3.6","breakV":7.5,"isShortCircuit":false},{"uid":1499653911649,"classname":"SimpleCoilSkin","cateid":"1","positionX":-271.00426232438093,"positionY":4128.117099059516,"rotation":0,"loadLevel":5,"notexture":"0","isBreak":false,"Resistance":59.99999999999999,"Power":0,"hasReversal":false,"hasMagReversal":false,"showMagLine":false,"hasIronCore":false,"inductance":"0.0001"},{"uid":1499653902825,"classname":"ElecSinglePloeSingleThrowSwitch","cateid":"1","positionX":40.370882824018125,"positionY":4565.544200427338,"rotation":0,"loadLevel":5,"notexture":"0","isBreak":true,"flagLabel":"S1","Resistance":0.00001,"Power":0,"hasReversal":false,"hasMagReversal":false,"flabel1txt":"S","flabel2txt":"1","daoRotation":-0.7573076395604649},{"uid":1499653917451,"classname":"ElecWire","cateid":"1","positionX":0,"positionY":0,"rotation":0,"loadLevel":4,"notexture":"0","isBreak":false,"Resistance":0.00001,"Power":0,"hasReversal":false,"hasMagReversal":false,"isDrawType":true,"colorIndex":0,"h1_x":-365.1251654748359,"h1_y":3855.1537689417532,"h2_x":-409.9542623243809,"h2_y":4184.567099059515,"h1IsNearToBinding":true,"h2IsNearToBinding":true,"pArr":[{"x":-365.1251654748359,"y":3855.1537689417532},{"x":-465.26926294758033,"y":3904.512922145154},{"x":-517.5750501057817,"y":3999.193285434388},{"x":-501.2942123179473,"y":4101.453649432288},{"x":-432.7102341231148,"y":4178.200631201523},{"x":-409.9542623243809,"y":4184.567099059515}]},{"uid":1499653919105,"classname":"ElecWire","cateid":"1","positionX":0,"positionY":0,"rotation":0,"loadLevel":4,"notexture":"0","isBreak":false,"Resistance":0.00001,"Power":0,"hasReversal":false,"hasMagReversal":false,"isDrawType":true,"colorIndex":0,"h1_x":-193.0751654748359,"h1_y":3855.1537689417532,"h2_x":-127.00426232438093,"h2_y":4184.567099059515,"h1IsNearToBinding":true,"h2IsNearToBinding":true,"pArr":[{"x":-193.0751654748359,"y":3855.1537689417532},{"x":-78.25923365495582,"y":3910.1069866782564},{"x":-19.513992361061952,"y":4022.7901996398828},{"x":-33.786699714089565,"y":4129.608848501079},{"x":-104.96753113534301,"y":4205.995686009702},{"x":-127.00426232438093,"y":4184.567099059515}]},{"uid":1499653923448,"classname":"ElecWire","cateid":"1","positionX":0,"positionY":0,"rotation":0,"loadLevel":4,"notexture":"0","isBreak":false,"Resistance":0.00001,"Power":0,"hasReversal":false,"hasMagReversal":false,"isDrawType":true,"colorIndex":0,"h1_x":-127.00426232438093,"h1_y":4184.567099059515,"h2_x":143.67088282401812,"h2_y":4590.194200427338,"h1IsNearToBinding":true,"h2IsNearToBinding":true,"pArr":[{"x":-127.00426232438093,"y":4184.567099059515},{"x":-35.55298583118283,"y":4247.006629920499},{"x":98.57048208889373,"y":4278.854451019862},{"x":220.92184618975136,"y":4302.632747302768},{"x":282.8920891490497,"y":4400.033848259144},{"x":298.5840626385316,"y":4504.480536588321},{"x":210.8697235533046,"y":4565.828397796502},{"x":143.67088282401812,"y":4590.194200427338}]},{"uid":1499653925586,"classname":"ElecWire","cateid":"1","positionX":0,"positionY":0,"rotation":0,"loadLevel":4,"notexture":"0","isBreak":false,"Resistance":0.00001,"Power":0,"hasReversal":false,"hasMagReversal":false,"isDrawType":true,"colorIndex":0,"h1_x":-67.67911717598187,"h1_y":4590.194200427338,"h2_x":-505.99230561855063,"h2_y":4575.2238763979085,"h1IsNearToBinding":true,"h2IsNearToBinding":true,"pArr":[{"x":-67.67911717598187,"y":4590.194200427338},{"x":-199.52551436645433,"y":4608.233178181964},{"x":-313.71047032868546,"y":4602.757358958769},{"x":-414.67466853301335,"y":4589.163028025724},{"x":-505.99230561855063,"y":4575.2238763979085}]},{"uid":1499653928665,"classname":"ElecWire","cateid":"1","positionX":0,"positionY":0,"rotation":0,"loadLevel":4,"notexture":"0","isBreak":false,"Resistance":0.00001,"Power":0,"hasReversal":false,"hasMagReversal":false,"isDrawType":true,"colorIndex":0,"h1_x":-708.9923056185506,"h1_y":4575.2238763979085,"h2_x":-409.9542623243809,"h2_y":4184.567099059515,"h1IsNearToBinding":true,"h2IsNearToBinding":true,"pArr":[{"x":-708.9923056185506,"y":4575.2238763979085},{"x":-769.4344128328222,"y":4489.328855469348},{"x":-743.6867804240269,"y":4393.454790021029},{"x":-671.0339941781821,"y":4329.918174259994},{"x":-588.0822459992435,"y":4287.7295459258075},{"x":-499.8690518261322,"y":4243.469212558339},{"x":-419.98459922159617,"y":4192.32704824676},{"x":-409.9542623243809,"y":4184.567099059515}]}],"BTN_NAME":true},"title":"断电自感"}}}