{"formData":[],"seCompData":{"data":[]},"phyData":{"dataVersion":3,"id":"148281939092632","properties":{"data":{"containsVipequ":false,"version":1,"showElecLine":true,"SHOWEQUVALUE":true,"SHOWTIPPAO":true,"SHOW_FLAG_LABEL":true,"VOLUME":1,"OPEN_ANGLE":false,"SHOW_REFLECT":false,"SHOW_DIRECTION":false,"SHOW_ZULI":false,"COMP_MESS":true,"BTN_NAME":true,"ZULI_NUM":9.8,"confVer":"1.0.0","moduleData":{},"view":{"x":1040.088077742499,"y":-2368.409428493779,"scaleX":0.74255007327797,"scaleY":0.74255007327797},"backgroundColorImg":{"colors":{"direction":0,"arr":["#343941"],"style":{"background":"#343941"}},"textureSelected":0},"dataArr":[{"uid":1482819351890,"classname":"ElecSinglePloeSingleThrowSwitch","cateid":"1","positionX":131.00004031243395,"positionY":4600.207207265911,"rotation":0,"loadLevel":5,"notexture":"0","isBreak":true,"flagLabel":"S1","Resistance":0.00001,"Power":0,"hasReversal":false,"hasMagReversal":false,"flabel1txt":"S","flabel2txt":"1","daoRotation":-0.7302064657477524,"posts":[{"UID":"3678603738357"},{"UID":"3314669277336"}]},{"uid":1482819361531,"classname":"ElecMotors","cateid":"1","positionX":766.999990458594,"positionY":4060.0113404228114,"rotation":0,"loadLevel":5,"notexture":"0","isBreak":false,"flagLabel":"M1","Resistance":2,"Power":0,"hasReversal":false,"hasMagReversal":false,"flabel1txt":"M","flabel2txt":"1","ratedV":3,"stopR":2,"posts":[{"UID":"4317002407654"},{"UID":"3423509599328"}]},{"uid":1482819357088,"classname":"ElecSlideRheostat","cateid":"1","positionX":787.999996302704,"positionY":4602.207736635811,"rotation":0,"loadLevel":5,"notexture":"0","isBreak":false,"Resistance":0.00001,"Power":0,"hasReversal":false,"hasMagReversal":false,"flabel1txt":"R","flabel2txt":"1","dragerX":2.9999910549362,"maxRes":20,"canFuse":false,"fuseValue":2,"posts":[{"UID":"4584813934669"},{"UID":"3624389196807"},{"UID":"4277500968940"},{"UID":"3966300172623"}]},{"uid":1482819375318,"classname":"ElecSinglePloeSingleThrowSwitch","cateid":"1","positionX":255.99999999999397,"positionY":3948.0346326961107,"rotation":0,"loadLevel":5,"notexture":"0","isBreak":true,"flagLabel":"S2","Resistance":0.00001,"Power":0,"hasReversal":false,"hasMagReversal":false,"flabel1txt":"S","flabel2txt":"2","daoRotation":-0.48,"posts":[{"UID":"3533724574839"},{"UID":"3705699915567"}]},{"uid":1482819364896,"classname":"InlandAmpereMeter","cateid":"1","positionX":-256.99994847642597,"positionY":4094.1262136795112,"rotation":0,"loadLevel":5,"notexture":"0","isBreak":false,"flagLabel":"A1","Resistance":0.00001,"Power":0,"hasReversal":false,"hasMagReversal":false,"flabel1txt":"A","flabel2txt":"1","validNum":2,"bar2Resistance":0.00007,"posts":[{"UID":"3652567793896"},{"UID":"4510603876060"},{"UID":"3464437414129"}]},{"uid":1482819351140,"classname":"BatteryHolder","cateid":"1","positionX":-380.99994108184603,"positionY":4586.203501677012,"rotation":0,"loadLevel":5,"notexture":"0","isBreak":false,"flagLabel":"E1","Resistance":0.00001,"Power":3,"hasReversal":false,"hasMagReversal":false,"flabel1txt":"E","flabel2txt":"1","posts":[{"UID":"3629959880179"},{"UID":"4683807456903"}]},{"uid":1562061924363,"classname":"ElecBuzzer","cateid":"1","positionX":339.51899442616536,"positionY":4183.893839082173,"rotation":0,"loadLevel":5,"notexture":"0","isBreak":false,"flagLabel":"H1","Resistance":10,"Power":0,"hasReversal":false,"hasMagReversal":false,"flabel1txt":"H","flabel2txt":"1","ratedV":3.5,"startV":0.5,"posts":[{"UID":"1562061924364"},{"UID":"3250876650198"}]},{"uid":1482819369058,"classname":"ElecWire","cateid":"1","positionX":0,"positionY":0,"rotation":0,"loadLevel":4,"notexture":"0","isBreak":false,"Resistance":0.00001,"Power":0,"hasReversal":false,"hasMagReversal":false,"isDrawType":true,"colorIndex":0,"h1_x":-215.99994108184603,"h1_y":4606.203501677012,"h2_x":22.950040312433956,"h2_y":4624.857207265911,"h1IsNearToBinding":true,"h2IsNearToBinding":true,"post0":{"UID":"4365694714502","driver":"4683807456903"},"post1":{"UID":"3842652700132","driver":"3678603738357"},"posts":[{"UID":"4365694714502"},{"UID":"3842652700132"}],"pArr":[{"x":-215.99994108184603,"y":4606.203501677012},{"x":-102.3427367655011,"y":4608.602885011441},{"x":9.595643432253752,"y":4625.04592429202},{"x":22.950040312433956,"y":4624.857207265911}]},{"uid":1482819370568,"classname":"ElecWire","cateid":"1","positionX":0,"positionY":0,"rotation":0,"loadLevel":4,"notexture":"0","isBreak":false,"Resistance":0.00001,"Power":0,"hasReversal":false,"hasMagReversal":false,"isDrawType":true,"colorIndex":0,"h1_x":234.30004031243396,"h1_y":4624.857207265911,"h2_x":620.999996302704,"h2_y":4632.157736635811,"h1IsNearToBinding":true,"h2IsNearToBinding":true,"post0":{"UID":"1562061872070","driver":"3314669277336"},"post1":{"UID":"4392665659459","driver":"4584813934669"},"posts":[{"UID":"1562061872070"},{"UID":"4392665659459"}],"pArr":[{"x":234.30004031243396,"y":4624.857207265911},{"x":352.3382887095479,"y":4627.93046092939},{"x":462.12604127292775,"y":4637.505002190352},{"x":572.9157579892177,"y":4630.9796146803155},{"x":620.999996302704,"y":4632.157736635811}]},{"uid":1482819372072,"classname":"ElecWire","cateid":"1","positionX":0,"positionY":0,"rotation":0,"loadLevel":4,"notexture":"0","isBreak":false,"Resistance":0.00001,"Power":0,"hasReversal":false,"hasMagReversal":false,"isDrawType":true,"colorIndex":0,"h1_x":982.499996302704,"h1_y":4530.157736635811,"h2_x":852.999990458594,"h2_y":4109.511340422811,"h1IsNearToBinding":true,"h2IsNearToBinding":true,"post0":{"UID":"3634855431707","driver":"3966300172623"},"post1":{"UID":"3717364120263","driver":"3423509599328"},"posts":[{"UID":"3634855431707"},{"UID":"3717364120263"}],"pArr":[{"x":982.499996302704,"y":4530.157736635811},{"x":1035.6140123568969,"y":4442.887221940151},{"x":1041.043091026342,"y":4350.836202014961},{"x":1028.5640043891794,"y":4252.405929110052},{"x":964.5876268140366,"y":4176.9276984549415},{"x":880.8863740325271,"y":4124.530804523393},{"x":852.999990458594,"y":4109.511340422811}]},{"uid":1482819373142,"classname":"ElecWire","cateid":"1","positionX":0,"positionY":0,"rotation":0,"loadLevel":4,"notexture":"0","isBreak":false,"Resistance":0.00001,"Power":0,"hasReversal":false,"hasMagReversal":false,"isDrawType":true,"colorIndex":0,"h1_x":678.449990458594,"h1_y":4109.511340422811,"h2_x":425.5189944261658,"h2_y":4194.543839082174,"h1IsNearToBinding":true,"h2IsNearToBinding":true,"post0":{"UID":"3314702713740","driver":"4317002407654"},"post1":{"UID":"4564895774113","driver":"3250876650198"},"posts":[{"UID":"3314702713740"},{"UID":"4564895774113"}],"pArr":[{"x":678.449990458594,"y":4109.511340422811},{"x":624.9707857672915,"y":4201.5680576617315},{"x":523.7427622959411,"y":4205.950002258264},{"x":425.5189944261658,"y":4194.543839082174}]},{"uid":1482819377034,"classname":"ElecWire","cateid":"1","positionX":0,"positionY":0,"rotation":0,"loadLevel":4,"notexture":"0","isBreak":false,"Resistance":0.00001,"Power":0,"hasReversal":false,"hasMagReversal":false,"isDrawType":true,"colorIndex":0,"h1_x":256.5189944261656,"h1_y":4194.543839082174,"h2_x":-179.99994847642597,"h2_y":4171.126213679511,"h1IsNearToBinding":true,"h2IsNearToBinding":true,"post0":{"UID":"4001064523847","driver":"1562061924364"},"post1":{"UID":"3361521451075","driver":"3464437414129"},"posts":[{"UID":"4001064523847"},{"UID":"3361521451075"}],"pArr":[{"x":256.5189944261656,"y":4194.543839082174},{"x":155.0676885893683,"y":4194.795266110182},{"x":46.59964433332004,"y":4186.483629362561},{"x":-58.21126713206769,"y":4180.458576749706},{"x":-156.00544021920834,"y":4182.996587910209},{"x":-179.99994847642597,"y":4171.126213679511}]},{"uid":1482819378529,"classname":"ElecWire","cateid":"1","positionX":0,"positionY":0,"rotation":0,"loadLevel":4,"notexture":"0","isBreak":false,"Resistance":0.00001,"Power":0,"hasReversal":false,"hasMagReversal":false,"isDrawType":true,"colorIndex":0,"h1_x":-339.64994847642595,"h1_y":4169.926213679511,"h2_x":-540.999941081846,"h2_y":4606.203501677012,"h1IsNearToBinding":true,"h2IsNearToBinding":true,"post0":{"UID":"3425080017885","driver":"3652567793896"},"post1":{"UID":"4394081781434","driver":"3629959880179"},"posts":[{"UID":"3425080017885"},{"UID":"4394081781434"}],"pArr":[{"x":-339.64994847642595,"y":4169.926213679511},{"x":-442.8079320711479,"y":4187.45958354307},{"x":-550.5873838895216,"y":4249.511724081834},{"x":-644.483695589773,"y":4314.4938441499935},{"x":-720.8734033700533,"y":4406.072458987674},{"x":-676.5985236354179,"y":4506.71419873141},{"x":-585.6126154919407,"y":4567.387223466599},{"x":-540.999941081846,"y":4606.203501677012}]},{"uid":1482819379851,"classname":"ElecWire","cateid":"1","positionX":0,"positionY":0,"rotation":0,"loadLevel":4,"notexture":"0","isBreak":false,"Resistance":0.00001,"Power":0,"hasReversal":false,"hasMagReversal":false,"isDrawType":true,"colorIndex":0,"h1_x":147.94999999999396,"h1_y":3972.684632696111,"h2_x":256.5189944261656,"h2_y":4194.543839082174,"h1IsNearToBinding":true,"h2IsNearToBinding":true,"post0":{"UID":"3634555468077","driver":"3533724574839"},"post1":{"UID":"4192708052568","driver":"1562061924364"},"posts":[{"UID":"3634555468077"},{"UID":"4192708052568"}],"pArr":[{"x":147.94999999999396,"y":3972.684632696111},{"x":138.7588923512022,"y":4092.102795532915},{"x":234.10536409463108,"y":4181.40000010041},{"x":256.5189944261656,"y":4194.543839082174}]},{"uid":1482819382591,"classname":"ElecWire","cateid":"1","positionX":0,"positionY":0,"rotation":0,"loadLevel":4,"notexture":"0","isBreak":false,"Resistance":0.00001,"Power":0,"hasReversal":false,"hasMagReversal":false,"isDrawType":true,"colorIndex":0,"h1_x":359.299999999994,"h1_y":3972.684632696111,"h2_x":425.5189944261658,"h2_y":4194.543839082174,"h1IsNearToBinding":true,"h2IsNearToBinding":true,"post0":{"UID":"3180648852966","driver":"3705699915567"},"post1":{"UID":"3907323867458","driver":"3250876650198"},"posts":[{"UID":"3180648852966"},{"UID":"3907323867458"}],"pArr":[{"x":359.299999999994,"y":3972.684632696111},{"x":405.9788516499766,"y":4056.508078235985},{"x":422.965970663768,"y":4147.673497397675},{"x":425.5189944261658,"y":4194.543839082174}]}]},"title":"蜂鸣器和小电机"}}}