{"formData":[],"sensorData":{"data":[]},"seCompData":{"data":[]},"phyData":{"dataVersion":3,"id":"148420560439087","DISComp":{"UID":"1576489632858"},"properties":{"data":{"containsVipequ":true,"version":1,"showElecLine":true,"SHOWEQUVALUE":true,"SHOWTIPPAO":true,"SHOW_FLAG_LABEL":true,"VOLUME":1,"OPEN_ANGLE":false,"SHOW_REFLECT":false,"SHOW_DIRECTION":false,"SHOW_ZULI":false,"COMP_MESS":true,"BTN_NAME":true,"ZULI_NUM":9.8,"confVer":"1.0.0","moduleData":{},"view":{"x":1888.4407816256319,"y":-5482.413229441605,"scaleX":1.4485319266684697,"scaleY":1.4485319266684697},"backgroundColorImg":{"colors":{"direction":0,"arr":["#343941"],"style":{"background":"#343941"}},"textureSelected":0},"dataArr":[{"uid":1484205548301,"classname":"WireRetainingClip","cateid":"1","positionX":-587.5027662044379,"positionY":4158.161540077473,"rotation":0,"loadLevel":5,"notexture":"0","isBreak":false,"Resistance":0.00001,"Power":0,"hasReversal":false,"hasMagReversal":false,"showMagLine":false,"hasIronCore":false,"posts":[{"UID":"3774205311383"},{"UID":"4376426628503"},{"UID":"3422402866806"},{"UID":"4323143734168"}]},{"uid":1484205550810,"classname":"WireRetainingClip","cateid":"1","positionX":-95.50276620443287,"positionY":4167.163231727874,"rotation":0,"loadLevel":5,"notexture":"0","isBreak":false,"Resistance":0.00001,"Power":0,"hasReversal":false,"hasMagReversal":false,"showMagLine":false,"hasIronCore":false,"posts":[{"UID":"3642397181784"},{"UID":"4678610979872"},{"UID":"4259106897965"},{"UID":"3993814031249"}]},{"uid":1484205541015,"classname":"ElecSlideRheostat","cateid":"1","positionX":245.16104932904432,"positionY":4598.361651349577,"rotation":0,"loadLevel":5,"flabel1txt":"R","flabel2txt":"1","notexture":"0","isBreak":false,"Resistance":0.00001,"Power":0,"hasReversal":false,"hasMagReversal":false,"dragerX":-39,"maxRes":20,"canFuse":false,"fuseValue":2,"posts":[{"UID":"1576489635232"},{"UID":"3274259213087"},{"UID":"3744747794522"},{"UID":"4068109379298"}]},{"uid":1484205538071,"classname":"ElecSinglePloeSingleThrowSwitch","cateid":"1","positionX":-277.1794118372393,"positionY":4596.067015563279,"rotation":0,"loadLevel":5,"flabel1txt":"S","flabel2txt":"1","notexture":"0","isBreak":true,"flagLabel":"S1","Resistance":0.00001,"Power":0,"hasReversal":false,"hasMagReversal":false,"daoRotation":-0.5086207780289294,"posts":[{"UID":"3706074470082"},{"UID":"4093903908460"}]},{"uid":1484205534761,"classname":"BatteryHolder","cateid":"1","positionX":-749.5113196039906,"positionY":4599.052903400641,"rotation":0,"loadLevel":5,"flabel1txt":"E","flabel2txt":"1","notexture":"0","isBreak":false,"flagLabel":"E1","Resistance":0.00001,"Power":3,"hasReversal":false,"hasMagReversal":false,"posts":[{"UID":"4364608975382"},{"UID":"4659034137368"}]},{"uid":1484205559435,"classname":"ElecWire","cateid":"1","positionX":0,"positionY":0,"rotation":0,"loadLevel":4,"notexture":"0","isBreak":false,"Resistance":0.00001,"Power":0,"hasReversal":false,"hasMagReversal":false,"isDrawType":true,"colorIndex":0,"h1_x":-584.5113196039905,"h1_y":4619.052903400641,"h2_x":-385.22941183723924,"h2_y":4620.717015563278,"h1IsNearToBinding":true,"h2IsNearToBinding":true,"post0":{"UID":"4661994013925","driver":"4659034137368"},"post1":{"UID":"4650826957287","driver":"3706074470082"},"posts":[{"UID":"4661994013925"},{"UID":"4650826957287"}],"pArr":[{"x":-584.5113196039905,"y":4619.052903400641},{"x":-496.4063316119115,"y":4617.322781629299},{"x":-411.833937436716,"y":4621.427876238995},{"x":-385.22941183723924,"y":4620.717015563278}]},{"uid":1484205570734,"classname":"ElecWire","cateid":"1","positionX":0,"positionY":0,"rotation":0,"loadLevel":4,"notexture":"0","isBreak":false,"Resistance":0.00001,"Power":0,"hasReversal":false,"hasMagReversal":false,"isDrawType":true,"colorIndex":0,"h1_x":-52.752766204432874,"h1_y":4352.513231727874,"h2_x":-136.25276620443287,"h2_y":4352.513231727874,"h1IsNearToBinding":true,"h2IsNearToBinding":true,"post0":{"UID":"3185914854327","driver":"3993814031249"},"post1":{"UID":"4342310217674","driver":"4678610979872"},"posts":[{"UID":"3185914854327"},{"UID":"4342310217674"}],"pArr":[{"x":-52.752766204432874,"y":4352.513231727874},{"x":-85.33112167708093,"y":4315.701676840475},{"x":-119.2275770316939,"y":4339.593479659775},{"x":-136.25276620443287,"y":4352.513231727874}]},{"uid":1484205576669,"classname":"ElecWire","cateid":"1","positionX":0,"positionY":0,"rotation":0,"loadLevel":4,"notexture":"0","isBreak":false,"Resistance":0.00001,"Power":0,"hasReversal":false,"hasMagReversal":false,"isDrawType":true,"colorIndex":0,"h1_x":-135.25276620443287,"h1_y":4004.1132317278734,"h2_x":-56.752766204432874,"h2_y":4004.1132317278734,"h1IsNearToBinding":true,"h2IsNearToBinding":true,"post0":{"UID":"3853849147253","driver":"3642397181784"},"post1":{"UID":"3604103890352","driver":"4259106897965"},"posts":[{"UID":"3853849147253"},{"UID":"3604103890352"}],"pArr":[{"x":-135.25276620443287,"y":4004.1132317278734},{"x":-117.17041750252501,"y":3999.501191477373},{"x":-99.42292711693113,"y":3994.9745583989734},{"x":-81.64680560156128,"y":3994.4450275371746},{"x":-64.83231231899236,"y":4000.167374513974},{"x":-56.752766204432874,"y":4004.1132317278734}]},{"uid":1484205561866,"classname":"ElecWire","cateid":"1","positionX":0,"positionY":0,"rotation":0,"loadLevel":4,"notexture":"0","isBreak":false,"Resistance":0.00001,"Power":0,"hasReversal":false,"hasMagReversal":false,"isDrawType":true,"colorIndex":0,"h1_x":-173.87941183723933,"h1_y":4620.717015563278,"h2_x":78.16104932904454,"h2_y":4628.311651349577,"h1IsNearToBinding":true,"h2IsNearToBinding":true,"post0":{"UID":"3902402010399","driver":"4093903908460"},"post1":{"UID":"3678768214124","driver":"1576489635232"},"posts":[{"UID":"3902402010399"},{"UID":"3678768214124"}],"pArr":[{"x":-173.87941183723933,"y":4620.717015563278},{"x":-51.73137994710298,"y":4629.258047286862},{"x":66.47157851539696,"y":4629.500070213827},{"x":78.16104932904454,"y":4628.311651349577}]},{"uid":1484205584008,"classname":"ElecWire","cateid":"1","positionX":0,"positionY":0,"rotation":0,"loadLevel":4,"notexture":"0","isBreak":false,"Resistance":0.00001,"Power":0,"hasReversal":false,"hasMagReversal":false,"isDrawType":true,"colorIndex":0,"h1_x":-135.25276620443287,"h1_y":4004.1132317278734,"h2_x":-548.7527662044379,"h2_y":3995.1115400774725,"h1IsNearToBinding":true,"h2IsNearToBinding":true,"post0":{"UID":"3945502559469","driver":"3642397181784"},"post1":{"UID":"4277255961711","driver":"3422402866806"},"posts":[{"UID":"3945502559469"},{"UID":"4277255961711"}],"pArr":[{"x":-135.25276620443287,"y":4004.1132317278734},{"x":-226.60936515982087,"y":3999.8673157954745},{"x":-316.35009768802786,"y":3989.551089291873},{"x":-406.0338403361678,"y":3981.2337911644727},{"x":-498.9493158386879,"y":3985.0571141796718},{"x":-548.7527662044379,"y":3995.1115400774725}]},{"uid":1484205586502,"classname":"ElecWire","cateid":"1","positionX":0,"positionY":0,"rotation":0,"loadLevel":4,"notexture":"0","isBreak":false,"Resistance":0.00001,"Power":0,"hasReversal":false,"hasMagReversal":false,"isDrawType":true,"colorIndex":0,"h1_x":-544.7527662044379,"h1_y":4343.511540077473,"h2_x":-628.2527662044379,"h2_y":4343.511540077473,"h1IsNearToBinding":true,"h2IsNearToBinding":true,"post0":{"UID":"4553063062721","driver":"4323143734168"},"post1":{"UID":"3840717832065","driver":"4376426628503"},"posts":[{"UID":"4553063062721"},{"UID":"3840717832065"}],"pArr":[{"x":-544.7527662044379,"y":4343.511540077473},{"x":-561.2137792243979,"y":4307.353438849773},{"x":-579.7116540769979,"y":4301.9886640169725},{"x":-597.7545858698179,"y":4308.484131303373},{"x":-615.1292609295679,"y":4314.739025727274},{"x":-628.2527662044379,"y":4343.511540077473}]},{"uid":1576489639690,"classname":"ElecWire","cateid":"1","positionX":-924.7339175457196,"positionY":4212.773616331379,"rotation":0,"loadLevel":4,"notexture":"0","isBreak":false,"flagLabel":"","Resistance":0,"Power":0,"hasReversal":false,"hasMagReversal":false,"isDrawType":false,"colorIndex":0,"h1_x":15.22259794172902,"h1_y":406.27928706926195,"h2_x":297.4811513412817,"h2_y":-217.66207625390695,"h1IsNearToBinding":true,"h2IsNearToBinding":true,"post0":{"UID":"4569354481863","driver":"4364608975382"},"post1":{"UID":"3294686077973","driver":"3774205311383"},"posts":[{"UID":"4569354481863"},{"UID":"3294686077973"}],"pArr":[{"x":15.22259794172902,"y":406.27928706926195},{"x":11.745072829233393,"y":-221.4458491808026},{"x":297.4811513412817,"y":-217.66207625390695}]},{"uid":1576489653139,"classname":"ElecWire","cateid":"1","positionX":122.29266972108417,"positionY":4327.008585511919,"rotation":0,"loadLevel":4,"notexture":"0","isBreak":false,"flagLabel":"","Resistance":0,"Power":0,"hasReversal":false,"hasMagReversal":false,"isDrawType":false,"colorIndex":0,"h1_x":-175.04543592551727,"h1_y":25.50464621595495,"h2_x":317.3683796079599,"h2_y":199.30306583765844,"h1IsNearToBinding":true,"h2IsNearToBinding":true,"post0":{"UID":"3274625356700","driver":"3993814031249"},"post1":{"UID":"4414436275515","driver":"4068109379298"},"posts":[{"UID":"3274625356700"},{"UID":"4414436275515"}],"pArr":[{"x":-175.04543592551727,"y":25.50464621595495},{"x":324.22071357255595,"y":30.337348196712533},{"x":317.3683796079599,"y":199.30306583765844}]}]},"title":"通电导线间的相互作用"}}}