{"type":"sprite","x":0,"y":0,"name":"","0":{"x":162,"y":-17,"name":"switch04","type":"nbMovie","r":0,"sx":1,"sy":1,"a":1,"skewX":0,"skewY":0,"0":{"index":2,"0":{"type":"bitmap","libName":"锯齿波.png","x":-16,"y":-10,"r":0,"sx":1,"sy":1,"skewX":0,"skewY":0},"1":{"type":"bitmap","libName":"弹起.png","x":-22,"y":-14,"r":0,"sx":1,"sy":1,"skewX":0,"skewY":0}},"1":{"index":2,"0":{"type":"bitmap","libName":"锯齿波.png","x":-16,"y":-10,"r":0,"sx":1,"sy":1,"skewX":0,"skewY":0},"1":{"type":"bitmap","libName":"按下.png","x":-22,"y":-14,"r":0,"sx":1,"sy":1,"skewX":0,"skewY":0}}},"1":{"x":118,"y":-17,"name":"switch03","type":"nbMovie","r":0,"sx":1,"sy":1,"a":1,"skewX":0,"skewY":0,"0":{"index":2,"0":{"type":"bitmap","libName":"方波.png","x":-12,"y":-10,"r":0,"sx":1,"sy":1,"skewX":0,"skewY":0},"1":{"type":"bitmap","libName":"弹起.png","x":-22,"y":-14,"r":0,"sx":1,"sy":1,"skewX":0,"skewY":0}},"1":{"index":2,"0":{"type":"bitmap","libName":"方波.png","x":-12,"y":-10,"r":0,"sx":1,"sy":1,"skewX":0,"skewY":0},"1":{"type":"bitmap","libName":"按下.png","x":-22,"y":-14,"r":0,"sx":1,"sy":1,"skewX":0,"skewY":0}}},"2":{"x":162,"y":-48,"name":"switch02","type":"nbMovie","r":0,"sx":1,"sy":1,"a":1,"skewX":0,"skewY":0,"0":{"index":2,"0":{"type":"bitmap","libName":"余弦波.png","x":-15,"y":-10,"r":0,"sx":1,"sy":1,"skewX":0,"skewY":0},"1":{"type":"bitmap","libName":"弹起.png","x":-22,"y":-14,"r":0,"sx":1,"sy":1,"skewX":0,"skewY":0}},"1":{"index":2,"0":{"type":"bitmap","libName":"余弦波.png","x":-15,"y":-10,"r":0,"sx":1,"sy":1,"skewX":0,"skewY":0},"1":{"type":"bitmap","libName":"按下.png","x":-22,"y":-14,"r":0,"sx":1,"sy":1,"skewX":0,"skewY":0}}},"3":{"x":118,"y":-48,"name":"switch01","type":"nbMovie","r":0,"sx":1,"sy":1,"a":1,"skewX":0,"skewY":0,"0":{"index":2,"0":{"type":"bitmap","libName":"正弦波.png","x":-15,"y":-10,"r":0,"sx":1,"sy":1,"skewX":0,"skewY":0},"1":{"type":"bitmap","libName":"弹起.png","x":-22,"y":-14,"r":0,"sx":1,"sy":1,"skewX":0,"skewY":0}},"1":{"index":2,"0":{"type":"bitmap","libName":"正弦波.png","x":-15,"y":-10,"r":0,"sx":1,"sy":1,"skewX":0,"skewY":0},"1":{"type":"bitmap","libName":"按下.png","x":-22,"y":-14,"r":0,"sx":1,"sy":1,"skewX":0,"skewY":0}}},"4":{"x":118,"y":23,"name":"switch05","type":"nbMovie","r":0,"sx":1,"sy":1,"a":1,"skewX":0,"skewY":0,"0":{"index":1,"0":{"type":"bitmap","libName":"弹起.png","x":-22,"y":-14,"r":0,"sx":1,"sy":1,"skewX":0,"skewY":0}},"1":{"index":1,"0":{"type":"bitmap","libName":"按下.png","x":-22,"y":-14,"r":0,"sx":1,"sy":1,"skewX":0,"skewY":0}}},"5":{"x":-145,"y":60,"name":"light","type":"nbMovie","r":0,"sx":1,"sy":1,"a":1,"skewX":0,"skewY":0,"0":{"index":1,"0":{"type":"bitmap","libName":"指示灯关.png","x":-10,"y":-10,"r":0,"sx":1,"sy":1,"skewX":0,"skewY":0}},"1":{"index":1,"0":{"type":"bitmap","libName":"指示灯开.png","x":-10,"y":-10,"r":0,"sx":1,"sy":1,"skewX":0,"skewY":0}}},"6":{"x":158.7,"y":78.95,"name":"bp0","type":"sprite","r":0,"sx":1,"sy":1,"a":1,"skewX":0,"skewY":0,"0":{"type":"shape","path":[255,10,-10,2,-10,-10,2,-10,10,2,10,10,2,10,-10,2,10,-10,1,1,16777215,33]}},"7":{"x":110.75,"y":78.95,"name":"bp1","type":"sprite","r":0,"sx":1,"sy":1,"a":1,"skewX":0,"skewY":0,"0":{"type":"shape","path":[255,10,-10,2,-10,-10,2,-10,10,2,10,10,2,10,-10,2,10,-10,1,1,16777215,33]}},"8":{"x":61.1,"y":78.95,"name":"rot02","type":"sprite","r":0,"sx":0.9999847412109375,"sy":0.9999847412109375,"a":1,"skewX":0,"skewY":0,"0":{"type":"bitmap","libName":"旋钮指针.png","x":-11,"y":-11,"r":0,"sx":1,"sy":1,"skewX":0,"skewY":0},"1":{"x":0,"y":0,"name":"","type":"sprite","r":0,"sx":5.0000457763671875,"sy":0.7137451171875,"a":1,"skewX":0,"skewY":0,"0":{"type":"bitmap","libName":"Bitmap 1","x":-5,"y":-35,"r":0,"sx":1,"sy":1,"skewX":0,"skewY":0}}},"9":{"x":-5.9,"y":78.95,"name":"rot01","type":"sprite","r":0,"sx":0.9999847412109375,"sy":0.9999847412109375,"a":1,"skewX":0,"skewY":0,"0":{"type":"bitmap","libName":"旋钮指针.png","x":-11,"y":-11,"r":0,"sx":1,"sy":1,"skewX":0,"skewY":0},"1":{"x":0,"y":0,"name":"","type":"sprite","r":0,"sx":5.0000457763671875,"sy":0.7137451171875,"a":1,"skewX":0,"skewY":0,"0":{"type":"bitmap","libName":"Bitmap 1","x":-5,"y":-35,"r":0,"sx":1,"sy":1,"skewX":0,"skewY":0}}},"10":{"x":-73.9,"y":78.95,"name":"rot00","type":"sprite","r":0,"sx":0.9999847412109375,"sy":0.9999847412109375,"a":1,"skewX":0,"skewY":0,"0":{"type":"bitmap","libName":"旋钮指针.png","x":-11,"y":-11,"r":0,"sx":1,"sy":1,"skewX":0,"skewY":0},"1":{"x":0,"y":0,"name":"","type":"sprite","r":0,"sx":5.0000457763671875,"sy":0.7137451171875,"a":1,"skewX":0,"skewY":0,"0":{"type":"bitmap","libName":"Bitmap 1","x":-5,"y":-35,"r":0,"sx":1,"sy":1,"skewX":0,"skewY":0}}},"11":{"x":-143,"y":96,"name":"switch00","type":"nbMovie","r":0,"sx":1,"sy":1,"a":1,"skewX":0,"skewY":0,"0":{"index":1,"0":{"type":"bitmap","libName":"switch_off.png","x":-33.5,"y":-16,"r":0,"sx":1,"sy":1,"skewX":0,"skewY":0}},"1":{"index":1,"0":{"type":"bitmap","libName":"switch_on.png","x":-33.5,"y":-16,"r":0,"sx":1,"sy":1,"skewX":0,"skewY":0}}},"12":{"x":0,"y":0,"name":"bg","type":"sprite","r":0,"sx":1,"sy":1,"a":1,"skewX":0,"skewY":0,"0":{"type":"bitmap","libName":"信号发射器.png","x":-207,"y":-148,"r":0,"sx":1,"sy":1,"skewX":0,"skewY":0}}}