{"type":"sprite","x":0,"y":0,"name":"compnent","0":{"x":0,"y":-102.5,"name":"top","type":"nbMovie","r":0,"sx":1,"sy":1,"a":1,"skewX":0,"skewY":0,"0":{"index":1,"0":{"type":"bitmap","libName":"down.png","x":-20,"y":-35,"r":0,"sx":1,"sy":1,"skewX":0,"skewY":0}},"1":{"index":1,"0":{"type":"bitmap","libName":"自然.png","x":-20,"y":-35,"r":0,"sx":1,"sy":1,"skewX":0,"skewY":0}}},"1":{"type":"shape","path":[255,-58.05,-6.25,-66.75,-5.75,-66.9,-5.8,3,-66.9,-5.8,-66.95,-5.8,-66.9,0.2,3,-66.9,0.2,-66.8,6.25,-66.9,6.2,3,-66.9,6.2,-67.05,6.15,-58.05,6.65,3,-58.05,6.65,-58.2,6.6,-48.25,17.2,3,-48.25,17.2,-48.4,17.15,-17.1,15.75,3,-17.1,15.75,-17.25,15.7,7.75,12.65,3,7.75,12.65,27.05,8.65,26.9,8.6,3,26.9,8.6,138.1,1.95,137.95,1.9,3,137.95,1.9,137.9,1.9,137.85,0.6,3,137.85,0.6,137.8,-0.7,137.7,-0.75,3,137.7,-0.75,137.65,-1.05,28.15,-7.7,3,28.15,-7.7,2,6.1,-12.95,2,-16.65,-14.85,2,-48,-16.3,-48.05,-16.3,-53,-11.25,3,-53,-11.25,-57.95,-6.2,-58.05,-6.25,3,1,0,1,32]},"2":{"x":0,"y":0,"name":"bg","type":"sprite","r":0,"sx":1,"sy":1,"a":1,"skewX":0,"skewY":0,"0":{"x":-20,"y":-140.5,"name":"mc11","type":"sprite","r":0,"sx":1,"sy":1,"a":1,"skewX":0,"skewY":0,"0":{"type":"bitmap","libName":"1.png 副本","x":0,"y":0,"r":0,"sx":1,"sy":1,"skewX":0,"skewY":0}}}}