{"formData":[],"seCompData":{"data":[]},"phyData":{"dataVersion":3,"id":"148360627024806","properties":{"data":{"containsVipequ":true,"version":5,"showElecLine":true,"SHOWEQUVALUE":true,"SHOWTIPPAO":true,"SHOW_FLAG_LABEL":true,"VOLUME":1,"OPEN_ANGLE":false,"SHOW_REFLECT":false,"SHOW_DIRECTION":false,"SHOW_ZULI":false,"COMP_MESS":true,"BTN_NAME":true,"ZULI_NUM":9.8,"confVer":"1.0.0","view":{"x":1620.4698873643447,"y":-3683.5790768153174,"scaleX":1.0462016370907559,"scaleY":1.0462016370907559},"moduleData":{"isplay":true},"backgroundColorImg":{"colors":{"direction":0,"arr":["#343941"],"style":{"background":"#343941"}},"textureSelected":0},"dataArr":[{"uid":1483605492017,"classname":"NbDesk","cateid":"5","positionX":0,"positionY":0,"rotation":0,"loadLevel":5,"notexture":"0","ismecJoint":false,"isMechanics":true,"thisX":-859.2730281088624,"thisY":4655.812921812564,"fromEquTools":true,"posx":-859.2730281088624,"posy":4655.812921812564,"material":{"density":0.8,"elasticity":0,"dynamicFriction":1,"staticFriction":2,"rollingFriction":1},"transform":{"a":1,"b":0,"c":0,"d":1,"tx":0,"ty":0},"currentScale":{"x":1,"y":1}},{"uid":1483605516829,"classname":"Hockcode","cateid":"5","positionX":0,"positionY":0,"rotation":0,"loadLevel":5,"notexture":"0","ismecJoint":false,"isMechanics":true,"thisX":-580.1540109711306,"thisY":4490.012917289005,"fromEquTools":true,"posx":-580.1540109711306,"posy":4490.012917289005,"mass":"50g","material":{"density":2.7,"elasticity":0.3,"dynamicFriction":0.5,"staticFriction":0.6,"rollingFriction":0.001},"transform":{"a":1,"b":0,"c":0,"d":1,"tx":0,"ty":0},"currentScale":{"x":1,"y":1}},{"uid":1483605522544,"classname":"Hockcode","cateid":"5","positionX":0,"positionY":0,"rotation":0,"loadLevel":5,"notexture":"0","ismecJoint":false,"isMechanics":true,"thisX":-889.8180408464706,"thisY":4490.012921812564,"fromEquTools":true,"posx":-889.8180408464706,"posy":4490.012921812564,"mass":"50g","material":{"density":2.7,"elasticity":0.3,"dynamicFriction":0.5,"staticFriction":0.6,"rollingFriction":0.001},"transform":{"a":1,"b":0,"c":0,"d":1,"tx":0,"ty":0},"currentScale":{"x":1,"y":1}},{"uid":1483605518825,"classname":"Hockcode","cateid":"5","positionX":0,"positionY":0,"rotation":0,"loadLevel":5,"notexture":"0","ismecJoint":false,"isMechanics":true,"thisX":-685.9484341115563,"thisY":4490.0128982538545,"fromEquTools":true,"posx":-685.9484341115563,"posy":4490.0128982538545,"mass":"50g","material":{"density":2.7,"elasticity":0.3,"dynamicFriction":0.5,"staticFriction":0.6,"rollingFriction":0.001},"transform":{"a":1,"b":0,"c":0,"d":1,"tx":0,"ty":0},"currentScale":{"x":1,"y":1}},{"uid":1483605520751,"classname":"Hockcode","cateid":"5","positionX":0,"positionY":0,"rotation":0,"loadLevel":5,"notexture":"0","ismecJoint":false,"isMechanics":true,"thisX":-779.0090620624577,"thisY":4490.012864353072,"fromEquTools":true,"posx":-779.0090620624577,"posy":4490.012864353072,"mass":"50g","material":{"density":2.7,"elasticity":0.3,"dynamicFriction":0.5,"staticFriction":0.6,"rollingFriction":0.001},"transform":{"a":1,"b":0,"c":0,"d":1,"tx":0,"ty":0},"currentScale":{"x":1,"y":1}},{"uid":1483605496441,"classname":"PullComp","cateid":"5","positionX":0,"positionY":0,"rotation":0,"loadLevel":5,"notexture":"0","ismecJoint":false,"isMechanics":true,"thisX":44.89210042500888,"thisY":3927.297688743321,"fromEquTools":true,"posx":44.89210042500888,"posy":3927.297688743321,"topNum":1,"bottomNum":1,"track":true,"linetype":0,"allLen":750,"dhlMass":0,"material":{"density":2.7,"elasticity":0.3,"dynamicFriction":0.5,"staticFriction":0.6,"rollingFriction":0.001},"transform":{"a":1,"b":0,"c":0,"d":1,"tx":0,"ty":0},"currentScale":{"x":1,"y":1},"lhock":{"x":-93.54431073121575,"y":4241.799066130733}},{"uid":1565169444112,"classname":"Ruler","cateid":"5","positionX":0,"positionY":0,"rotation":4.71238898038469,"loadLevel":5,"notexture":"0","ismecJoint":false,"isMechanics":true,"thisX":363.8375281158217,"thisY":4166.103835182328,"fromEquTools":true,"posx":363.8375281158217,"posy":4166.103835182328,"selectType":"直尺","through":true,"divisionIndex":0,"rangeValue":20,"material":{"density":2.7,"elasticity":0.3,"dynamicFriction":0.5,"staticFriction":0.6,"rollingFriction":0.001},"transform":{"a":1,"b":0,"c":0,"d":1,"tx":0,"ty":0},"currentScale":{"x":1,"y":1}},{"uid":1483605524707,"classname":"Hockcode","cateid":"5","positionX":0,"positionY":0,"rotation":0,"loadLevel":5,"notexture":"0","ismecJoint":false,"isMechanics":true,"thisX":44.89210042500872,"thisY":4519.139504530547,"fromEquTools":true,"posx":44.89210042500872,"posy":4519.139504530547,"mass":"50g","material":{"density":2.7,"elasticity":0.3,"dynamicFriction":0.5,"staticFriction":0.6,"rollingFriction":0.001},"transform":{"a":1,"b":0,"c":0,"d":1,"tx":0,"ty":0},"currentScale":{"x":1,"y":1}},{"uid":1565169289287,"classname":"SpringTension","cateid":"5","positionX":0,"positionY":0,"rotation":3.485947540966659,"loadLevel":5,"notexture":"0","ismecJoint":false,"isMechanics":true,"thisX":247.66623872549644,"thisY":4262.358247904892,"fromEquTools":true,"posx":-170.37742610432426,"posy":4455.843994316405,"tl":0,"lockDir":0,"range":5,"trackLine":false,"droplock":true,"valuetype":0,"material":{"density":2.7,"elasticity":0.3,"dynamicFriction":0.5,"staticFriction":0.6,"rollingFriction":0.001},"transform":{"a":1,"b":0,"c":0,"d":1,"tx":0,"ty":0},"currentScale":{"x":1,"y":1},"biao":{"x":-190.8413078633478,"y":4512.925967726275},"springhock":{"uid":1565169289296,"classname":null,"cateid":5,"positionX":247.66623872549644,"positionY":4262.358247904892,"rotation":3.485947540966659,"loadLevel":5,"ismecJoint":false,"isMechanics":true,"thisX":-341.21271040027364,"thisY":-20.55313395242581,"fromEquTools":true,"posx":-93.54647167477717,"posy":4241.805113952466,"material":{"density":2.7,"elasticity":0.3,"dynamicFriction":0.5,"staticFriction":0.6,"rollingFriction":0.001},"transform":{"a":1,"b":0,"c":0,"d":1,"tx":0,"ty":0},"currentScale":{"x":1,"y":1}}},{"uid":1565169631922,"classname":"Ruler","cateid":"5","positionX":0,"positionY":0,"rotation":4.71238898038469,"loadLevel":5,"notexture":"0","ismecJoint":false,"isMechanics":true,"thisX":475.37644778949385,"thisY":4165.481960491817,"fromEquTools":true,"posx":475.37644778949385,"posy":4165.481960491817,"selectType":"直尺","through":true,"divisionIndex":0,"rangeValue":20,"material":{"density":2.7,"elasticity":0.3,"dynamicFriction":0.5,"staticFriction":0.6,"rollingFriction":0.001},"transform":{"a":1,"b":0,"c":0,"d":1,"tx":0,"ty":0},"currentScale":{"x":1,"y":1}}]},"title":"探究滑轮组的机械效率"}}}